.coveragerc
.mailmap
.testr.conf
AUTHORS
ChangeLog
HACKING.rst
LICENSE
MANIFEST.in
README.rst
requirements.txt
setup.cfg
setup.py
test-requirements.txt
tox.ini
doc/source/conf.py
doc/source/index.rst
doc/source/installation.rst
doc/source/readme.rst
doc/source/usage.rst
explode/__init__.py
explode.egg-info/PKG-INFO
explode.egg-info/SOURCES.txt
explode.egg-info/dependency_links.txt
explode.egg-info/entry_points.txt
explode.egg-info/not-zip-safe
explode.egg-info/requires.txt
explode.egg-info/top_level.txt
explode/tests/__init__.py
explode/tests/base.py
explode/tests/test_explode.py